mcp_semantic_scholar/__init__.py
mcp_semantic_scholar/semantic_scholar_search.py
mcp_semantic_scholar/semantic_scholar_server.py
mcp_server_semanticscholar-0.1.0.dist-info/METADATA
mcp_server_semanticscholar-0.1.0.dist-info/WHEEL
mcp_server_semanticscholar-0.1.0.dist-info/entry_points.txt
mcp_server_semanticscholar-0.1.0.dist-info/RECORD
