Metadata-Version: 2.4
Name: mcp-server-semanticscholar
Version: 0.1.0
Summary: MCP (Model Context Protocol) server for Semantic Scholar API
Project-URL: Homepage, https://github.com/JackKuo666/semanticscholar-MCP-Server
Project-URL: Repository, https://github.com/JackKuo666/semanticscholar-MCP-Server
Project-URL: Issues, https://github.com/JackKuo666/semanticscholar-MCP-Server/issues
Author-email: Jack Kuo <jack.kuo@example.com>
License: MIT
Classifier: Development Status :: 4 - Beta
Classifier: Intended Audience :: Developers
Classifier: License :: OSI Approved :: MIT License
Classifier: Programming Language :: Python :: 3
Classifier: Programming Language :: Python :: 3.8
Classifier: Programming Language :: Python :: 3.9
Classifier: Programming Language :: Python :: 3.10
Classifier: Programming Language :: Python :: 3.11
Classifier: Programming Language :: Python :: 3.12
Requires-Python: >=3.8
Requires-Dist: fastapi
Requires-Dist: httpx
Requires-Dist: mcp>=0.1.0
Requires-Dist: semanticscholar>=0.7.0
Requires-Dist: uvicorn
